{
  "collectionName": "components_typeface_typefaces",
  "info": {
    "displayName": "typeface",
    "description": ""
  },
  "options": {},
  "attributes": {
    "title": {
      "type": "string"
    },
    "aboutText": {
      "type": "richtext"
    },
    "specimen": {
      "type": "media",
      "multiple": false,
      "required": false,
      "allowedTypes": [
        "files",
        "images"
      ]
    },
    "price": {
      "type": "float",
      "required": true
    },
    "parola": {
      "type": "password"
    }
  }
}
